batcharray/__init__.py
batcharray/constants.py
batcharray/py.typed
batcharray/types.py
batcharray/array/__init__.py
batcharray/array/comparison.py
batcharray/array/indexing.py
batcharray/array/joining.py
batcharray/array/math.py
batcharray/array/permutation.py
batcharray/array/reduction.py
batcharray/array/slicing.py
batcharray/computation/__init__.py
batcharray/computation/array.py
batcharray/computation/auto.py
batcharray/computation/base.py
batcharray/computation/interface.py
batcharray/computation/masked_array.py
batcharray/nested/__init__.py
batcharray/nested/comparison.py
batcharray/nested/conversion.py
batcharray/nested/indexing.py
batcharray/nested/joining.py
batcharray/nested/math.py
batcharray/nested/permutation.py
batcharray/nested/pointwise.py
batcharray/nested/reduction.py
batcharray/nested/slicing.py
batcharray/nested/trigo.py
batcharray-0.3.0.dist-info/METADATA
batcharray-0.3.0.dist-info/WHEEL
batcharray-0.3.0.dist-info/licenses/LICENSE
batcharray-0.3.0.dist-info/RECORD
