Metadata-Version: 2.4
Name: batcharray
Version: 0.3.0
Dynamic: Maintainer
Dynamic: Maintainer-email
Summary: Functions to manipulate NumPy arrays
Project-URL: homepage, https://github.com/durandtibo/batcharray
Project-URL: repository, https://github.com/durandtibo/batcharray
Project-URL: documentation, https://durandtibo.github.io/batcharray/
Author-email: Thibaut Durand <durand.tibo+gh@gmail.com>
License-Expression: BSD-3-Clause
License-File: LICENSE
Keywords: array,batch,numpy,sequence
Classifier: Development Status :: 4 - Beta
Classifier: Intended Audience :: Developers
Classifier: Intended Audience :: Information Technology
Classifier: Intended Audience :: Science/Research
Classifier: License :: OSI Approved :: BSD License
Classifier: Operating System :: POSIX :: Linux
Classifier: Programming Language :: Python :: 3.10
Classifier: Programming Language :: Python :: 3.11
Classifier: Programming Language :: Python :: 3.12
Classifier: Programming Language :: Python :: 3.13
Classifier: Programming Language :: Python :: 3.14
Classifier: Topic :: Scientific/Engineering
Classifier: Topic :: Scientific/Engineering :: Artificial Intelligence
Classifier: Topic :: Software Development :: Libraries
Requires-Python: >=3.10
Requires-Dist: coola<1.0,>=0.11.0
Requires-Dist: numpy<3.0,>=1.22
Provides-Extra: all
